pygrs/__init__.py
pygrs/main.py
pygrs-0.1.dist-info/METADATA
pygrs-0.1.dist-info/WHEEL
pygrs-0.1.dist-info/licenses/LICENSE
pygrs-0.1.dist-info/RECORD
