Metadata-Version: 2.4
Name: pygrs
Version: 0.1
Summary: reverse search similiar images across multiple platforms
Project-URL: Github, https://github.com/Bakachii/PyGRS
Project-URL: Issues, https://github.com/Bakachii/PyGRS/issues
Author-email: bakachii <thebakachii@gmail.com>
License: BSD 3-Clause License
License-File: LICENSE
Classifier: License :: OSI Approved :: BSD License
Classifier: Operating System :: OS Independent
Classifier: Programming Language :: Python :: 3
Requires-Python: >=3.8
Requires-Dist: beautifulsoup4>=4.14.3
Requires-Dist: fake-useragent>=2.2.0
Requires-Dist: requests>=2.32.5
Requires-Dist: urllib3>=2.6.3
